llm_repl/__init__.py
llm_repl/__main__.py
llm_repl/exceptions.py
llm_repl/data/chatgpt/personalities/default.yml
llm_repl/llms/__init__.py
llm_repl/llms/chatgpt.py
llm_repl/llms/chatgpt4.py
llm_repl/repls/__init__.py
llm_repl/repls/http.py
llm_repl/repls/prompt_toolkit.py
llm_repl/repls/websocket.py
llm_repl-1.0.1.dist-info/LICENSE
llm_repl-1.0.1.dist-info/METADATA
llm_repl-1.0.1.dist-info/WHEEL
llm_repl-1.0.1.dist-info/entry_points.txt
llm_repl-1.0.1.dist-info/top_level.txt
llm_repl-1.0.1.dist-info/RECORD
