Metadata-Version: 2.1
Name: llm-repl
Version: 1.0.1
Summary: A REPL for ChatGPT
Author-email: Sebastiano Mariani <mariani.sebastiano@gmail.com>
Project-URL: homepage, https://github.com/Phat3/LLM-Repl
Project-URL: repository, https://github.com/Phat3/LLM-Repl.git
Classifier: Development Status :: 3 - Alpha
Classifier: Programming Language :: Python :: 3
Classifier: Operating System :: OS Independent
Classifier: License :: OSI Approved :: MIT License
Requires-Python: >=3.10
License-File: LICENSE
Requires-Dist: prompt-toolkit
Requires-Dist: rich
Requires-Dist: langchain ==0.0.261
Requires-Dist: openai
Requires-Dist: pydantic
Requires-Dist: websockets
Requires-Dist: fastapi
Requires-Dist: uvicorn
Requires-Dist: pinecone-client
Requires-Dist: jinja2
Requires-Dist: sse-starlette
Provides-Extra: dev
Requires-Dist: pylint ; extra == 'dev'
Requires-Dist: ipdb ; extra == 'dev'
Requires-Dist: black ; extra == 'dev'
Requires-Dist: pytest ; extra == 'dev'
Requires-Dist: mypy ; extra == 'dev'
Requires-Dist: pre-commit ; extra == 'dev'
